ecco_plot_widget/__init__.py
ecco_plot_widget/ecco_compatibility.py
ecco_plot_widget/plot.py
ecco_plot_widget/utility.py
ecco_plot_widget/widget.py
ecco_plot_widget-1.0.0.dist-info/METADATA
ecco_plot_widget-1.0.0.dist-info/WHEEL
ecco_plot_widget-1.0.0.dist-info/licenses/LICENSE
ecco_plot_widget-1.0.0.dist-info/RECORD
